RsCMPX_Gprf/RsCMPX_Gprf.py
RsCMPX_Gprf/__init__.py
RsCMPX_Gprf/enums.py
RsCMPX_Gprf/repcap.py
RsCMPX_Gprf/CustomFiles/__init__.py
RsCMPX_Gprf/CustomFiles/events.py
RsCMPX_Gprf/CustomFiles/reliability.py
RsCMPX_Gprf/CustomFiles/utilities.py
RsCMPX_Gprf/Implementations/__init__.py
RsCMPX_Gprf/Implementations/Add/__init__.py
RsCMPX_Gprf/Implementations/Add/System/__init__.py
RsCMPX_Gprf/Implementations/Add/System/Attenuation/__init__.py
RsCMPX_Gprf/Implementations/Add/System/Attenuation/CorrectionTable/Globale.py
RsCMPX_Gprf/Implementations/Add/System/Attenuation/CorrectionTable/Tenvironment.py
RsCMPX_Gprf/Implementations/Add/System/Attenuation/CorrectionTable/__init__.py
RsCMPX_Gprf/Implementations/Add/Tenvironment/__init__.py
RsCMPX_Gprf/Implementations/Add/Tenvironment/Spath/__init__.py
RsCMPX_Gprf/Implementations/Add/Tenvironment/Spath/CorrectionTable/Rx.py
RsCMPX_Gprf/Implementations/Add/Tenvironment/Spath/CorrectionTable/Tx.py
RsCMPX_Gprf/Implementations/Add/Tenvironment/Spath/CorrectionTable/__init__.py
RsCMPX_Gprf/Implementations/Calibration/__init__.py
RsCMPX_Gprf/Implementations/Calibration/Gprf/__init__.py
RsCMPX_Gprf/Implementations/Calibration/Gprf/Measurement/__init__.py
RsCMPX_Gprf/Implementations/Calibration/Gprf/Measurement/ExtPwrSensor/Zero.py
RsCMPX_Gprf/Implementations/Calibration/Gprf/Measurement/ExtPwrSensor/__init__.py
RsCMPX_Gprf/Implementations/Catalog/__init__.py
RsCMPX_Gprf/Implementations/Catalog/Bluetooth/__init__.py
RsCMPX_Gprf/Implementations/Catalog/Bluetooth/Measurement/Spath.py
RsCMPX_Gprf/Implementations/Catalog/Bluetooth/Measurement/__init__.py
RsCMPX_Gprf/Implementations/Catalog/Cdma/__init__.py
RsCMPX_Gprf/Implementations/Catalog/Cdma/Measurement/Spath.py
RsCMPX_Gprf/Implementations/Catalog/Cdma/Measurement/__init__.py
RsCMPX_Gprf/Implementations/Catalog/Gprf/__init__.py
RsCMPX_Gprf/Implementations/Catalog/Gprf/Generator/__init__.py
RsCMPX_Gprf/Implementations/Catalog/Gprf/Generator/Spath/Group.py
RsCMPX_Gprf-5.0.92.dist-info/METADATA
RsCMPX_Gprf-5.0.92.dist-info/WHEEL
RsCMPX_Gprf-5.0.92.dist-info/top_level.txt
RsCMPX_Gprf-5.0.92.dist-info/RECORD
